lite_kits/__init__.py
lite_kits/cli.py
lite_kits/core/__init__.py
lite_kits/core/banner.py
lite_kits/core/conflict_checker.py
lite_kits/core/detector.py
lite_kits/core/installer.py
lite_kits/core/manifest.py
lite_kits/core/validator.py
lite_kits/kits/README.md
lite_kits/kits/kits.yaml
lite_kits/kits/dev/README.md
lite_kits/kits/dev/commands/.claude/audit.md
lite_kits/kits/dev/commands/.claude/cleanup.md
lite_kits/kits/dev/commands/.claude/commit.md
lite_kits/kits/dev/commands/.claude/orient.md
lite_kits/kits/dev/commands/.claude/pr.md
lite_kits/kits/dev/commands/.claude/review.md
lite_kits/kits/dev/commands/.claude/stats.md
lite_kits/kits/dev/commands/.github/audit.prompt.md
lite_kits/kits/dev/commands/.github/cleanup.prompt.md
lite_kits/kits/dev/commands/.github/commit.prompt.md
lite_kits/kits/dev/commands/.github/orient.prompt.md
lite_kits/kits/dev/commands/.github/pr.prompt.md
lite_kits/kits/dev/commands/.github/review.prompt.md
lite_kits/kits/dev/commands/.github/stats.prompt.md
lite_kits/kits/multiagent/README.md
lite_kits/kits/multiagent/commands/.claude/sync.md
lite_kits/kits/multiagent/commands/.github/sync.prompt.md
lite_kits/kits/multiagent/memory/git-worktrees-protocol.md
lite_kits/kits/multiagent/memory/parallel-work-protocol.md
lite_kits/kits/multiagent/memory/pr-workflow-guide.md
lite_kits/kits/multiagent/templates/decision.md
lite_kits/kits/multiagent/templates/handoff.md
lite_kits/kits/multiagent/templates/session-log.md
lite_kits/kits/multiagent/templates/collaboration-structure/README.md
lite_kits-0.3.3.dist-info/METADATA
lite_kits-0.3.3.dist-info/WHEEL
lite_kits-0.3.3.dist-info/entry_points.txt
lite_kits-0.3.3.dist-info/licenses/LICENSE
lite_kits-0.3.3.dist-info/RECORD
