Metadata-Version: 2.4
Name: lite-kits
Version: 0.3.3
Summary: Lightweight enhancement kits for vanilla dev tools (spec-kit, etc.)
Project-URL: Homepage, https://github.com/tmorgan181/lite-kits
Project-URL: Documentation, https://github.com/tmorgan181/lite-kits#readme
Project-URL: Repository, https://github.com/tmorgan181/lite-kits
Project-URL: Issues, https://github.com/tmorgan181/lite-kits/issues
Author: lite-kits contributors
License: MIT
License-File: LICENSE
Keywords: ai,development-workflow,enhancement,git,kits,spec-kit
Classifier: Development Status :: 4 - Beta
Classifier: Intended Audience :: Developers
Classifier: License :: OSI Approved :: MIT License
Classifier: Programming Language :: Python :: 3
Classifier: Programming Language :: Python :: 3.11
Classifier: Programming Language :: Python :: 3.12
Classifier: Topic :: Software Development :: Libraries :: Python Modules
Requires-Python: >=3.11
Requires-Dist: pyyaml>=6.0.0
Requires-Dist: rich>=13.0.0
Requires-Dist: typer>=0.9.0
Provides-Extra: dev
Requires-Dist: pytest-cov>=4.0.0; extra == 'dev'
Requires-Dist: pytest>=7.0.0; extra == 'dev'
Requires-Dist: ruff>=0.1.0; extra == 'dev'
